py_openjvs/__init__.py
py_openjvs/__main__.py
py_openjvs/jvs.py
py_openjvs/jvs_constants.py
py_openjvs/jvs_master.cfg
py_openjvs/jvs_master.py
py_openjvs/jvs_snoop.py
py_openjvs-2.0.1.data/data/config/jvs_master.cfg
py_openjvs-2.0.1.dist-info/LICENSE
py_openjvs-2.0.1.dist-info/METADATA
py_openjvs-2.0.1.dist-info/WHEEL
py_openjvs-2.0.1.dist-info/top_level.txt
py_openjvs-2.0.1.dist-info/RECORD
