Metadata-Version: 2.1
Name: py-openjvs
Version: 2.0.1
Summary: Packaged version of openjvs dev by Roy Smeding https://github.com/TheOnlyJoey/openjvs
Home-page: https://gitlab.com/gaper-private/openjvs
Author: Roy Smeding
Author-email: roy.smeding@gmail.com
License: UNKNOWN
Project-URL: Bug Tracker, https://gitlab.com/gaper-private/openjvs/issues
Platform: UNKNOWN
Classifier: Programming Language :: Python :: 3
Classifier: Operating System :: POSIX :: Linux
Requires-Python: >=3
License-File: LICENSE
Requires-Dist: python-uinput (>=0.11.2)
Requires-Dist: python-daemon (>=2.3.0)
Requires-Dist: pyserial (>=3.5)
Requires-Dist: configparser (>=5.0.2)
